django_discussions/__init__.py
django_discussions/admin.py
django_discussions/apps.py
django_discussions/models.py
django_discussions/urls.py
django_discussions/views.py
django_discussions/management/__init__.py
django_discussions/management/commands/__init__.py
django_discussions/migrations/0001_initial.py
django_discussions/migrations/__init__.py
django_discussions/static/django_discussions/styles.css
django_discussions/templates/django_discussions/_comment.html
django_discussions/templates/django_discussions/_comment_form.html
django_discussions/templates/django_discussions/_comments_section.html
django_discussions/templates/django_discussions/_thread_detail.html
django_discussions/templates/django_discussions/_thread_form.html
django_discussions/templates/django_discussions/_thread_header.html
django_discussions/templates/django_discussions/create_comment.html
django_discussions/templates/django_discussions/index.html
django_discussions/templates/django_discussions/thread_detail.html
django_discussions/templatetags/__init__.py
django_discussions/templatetags/discussion_tags.py
django_threaded_discussions-0.1.0.dist-info/METADATA
django_threaded_discussions-0.1.0.dist-info/WHEEL
django_threaded_discussions-0.1.0.dist-info/licenses/LICENSE
django_threaded_discussions-0.1.0.dist-info/RECORD
