Metadata-Version: 2.4
Name: django-threaded-discussions
Version: 0.1.0
Summary: Standalone Django app for threaded discussions with HTMX support
Project-URL: Homepage, https://github.com/directory-platform/django-threaded-discussions
Project-URL: Repository, https://github.com/directory-platform/django-threaded-discussions
Project-URL: Issues, https://github.com/directory-platform/django-threaded-discussions/issues
Author: Directory Platform Team
License: MIT
License-File: LICENSE
Keywords: comments,discussions,django,forum,htmx,threads
Classifier: Development Status :: 4 - Beta
Classifier: Environment :: Web Environment
Classifier: Framework :: Django
Classifier: Framework :: Django :: 4.2
Classifier: Framework :: Django :: 5.0
Classifier: Framework :: Django :: 5.1
Classifier: Intended Audience :: Developers
Classifier: License :: OSI Approved :: MIT License
Classifier: Operating System :: OS Independent
Classifier: Programming Language :: Python
Classifier: Programming Language :: Python :: 3
Classifier: Programming Language :: Python :: 3.12
Classifier: Topic :: Internet :: WWW/HTTP
Classifier: Topic :: Internet :: WWW/HTTP :: Dynamic Content
Classifier: Topic :: Software Development :: Libraries :: Python Modules
Classifier: Typing :: Typed
Requires-Python: >=3.12
Requires-Dist: django>=4.2
Requires-Dist: shortuuid>=1.0.0
Provides-Extra: dev
Requires-Dist: django-stubs>=4.2.0; extra == 'dev'
Requires-Dist: faker>=20.0.0; extra == 'dev'
Requires-Dist: mypy>=1.7.0; extra == 'dev'
Requires-Dist: ruff>=0.1.0; extra == 'dev'
